tests/__init__.py
tests/test_client.py
tests/test_utils.py
yellowcard_business/__init__.py
yellowcard_business/client.py
yellowcard_business/exceptions.py
yellowcard_business/models.py
yellowcard_business/utils.py
yellowcard_business-0.1.21.dist-info/LICENSE
yellowcard_business-0.1.21.dist-info/METADATA
yellowcard_business-0.1.21.dist-info/WHEEL
yellowcard_business-0.1.21.dist-info/top_level.txt
yellowcard_business-0.1.21.dist-info/RECORD
