Metadata-Version: 2.1
Name: yellowcard-business
Version: 0.1.21
Summary: Python SDK for the YellowCard B2B API
Home-page: https://docs.yellowcard.engineering/
Author: Yellowcard B2B API Team
Author-email: your.email@example.com
License-File: LICENSE
Requires-Dist: annotated-types ==0.7.0
Requires-Dist: certifi ==2024.12.14
Requires-Dist: charset-normalizer ==3.4.1
Requires-Dist: exceptiongroup ==1.2.2
Requires-Dist: idna ==3.10
Requires-Dist: iniconfig ==2.0.0
Requires-Dist: packaging ==24.2
Requires-Dist: pluggy ==1.5.0
Requires-Dist: pydantic ==2.10.5
Requires-Dist: pydantic-core ==2.27.2
Requires-Dist: pytest ==8.3.4
Requires-Dist: python-dotenv ==1.0.1
Requires-Dist: requests ==2.32.3
Requires-Dist: tomli ==2.2.1
Requires-Dist: typing-extensions ==4.12.2
Requires-Dist: urllib3 ==2.3.0
